dreem_nap/__init__.py
dreem_nap/manipulator.py
dreem_nap/plotter old old.py
dreem_nap/plotter old.py
dreem_nap/plotter.py
dreem_nap/study.py
dreem_nap/util.py
dreem_nap-3.0.5.dist-info/WHEEL
dreem_nap-3.0.5.dist-info/METADATA
dreem_nap-3.0.5.dist-info/RECORD
