Metadata-Version: 2.1
Name: dreem_nap
Version: 3.0.5
Summary: New Analysis Pipeline (NAP). Visualize DREEM output.
Author-email: Yves Martin des Taillades <yves@martin.yt>
